[
        {
                "name": "Rock & Roll Palace",
                "description": "Un bar emblemático donde la música en vivo es la protagonista.",
                "address": "Av. Dr. Severo Ochoa, 6, 03503 Benidorm, Alicante",
                "phone": "5551234569",
                "profile_picture": "https://res.cloudinary.com/daxbjkj1j/image/upload/v1715625621/jvuhbzf6rcuniuvthpop.jpg",
                "banner_picture": "https://res.cloudinary.com/daxbjkj1j/image/upload/v1715625687/sg0rejgl5upr9wyjzrmz.png",
                "instagram": "https://www.instagram.com/rocknrollpalace",
                "tiktok": "https://www.tiktok.com/rocknrollpalace"
        },
        {
                "name": "Jazz Enclave",
                "description": "Una sala íntima donde el jazz resuena en cada rincón.",
                "address": "C. de Recoletos, 18, Salamanca, 28001 Madrid",
                "phone": "5559876543",
                "profile_picture": "https://res.cloudinary.com/daxbjkj1j/image/upload/v1715625597/yxbntimltkjuzd6hq2at.jpg",
                "banner_picture": "https://res.cloudinary.com/daxbjkj1j/image/upload/v1715625681/hnl93pcyhpeyqte1ap1s.png",
                "instagram": "https://www.instagram.com/jazzenclave",
                "tiktok": "https://www.tiktok.com/jazzenclave"
        },
        {
                "name": "Blues Alley",
                "description": "Un rincón acogedor donde el blues fluye como el whisky.",
                "address": "Carrer d'En Botella, 7, Ciutat Vella, 08001 Barcelona",
                "phone": "5554567890",
                "profile_picture": "https://res.cloudinary.com/daxbjkj1j/image/upload/v1715625579/rsnat6p9c59qzf3c5ngy.jpg",
                "banner_picture": "https://res.cloudinary.com/daxbjkj1j/image/upload/v1715625656/sks484ye2lagijaandzq.png",
                "instagram": "https://www.instagram.com/bluesalley",
                "tiktok": "https://www.tiktok.com/bluesalley"
        },
        {
                "name": "ElectroBeat",
                "description": "Una sala vibrante donde la música electrónica te lleva a otra dimensión.",
                "address": "Cta. de Sta. Inés, 4, Albaicín, 18010 Granada",
                "phone": "5557890123",
                "profile_picture": "https://res.cloudinary.com/daxbjkj1j/image/upload/v1715625609/tgtm6643ivbixftfuce5.jpg",
                "banner_picture": "https://res.cloudinary.com/daxbjkj1j/image/upload/v1715625667/egxrzm5vq2tr8up6dmw0.png",
                "instagram": "https://www.instagram.com/electrobeat",
                "tiktok": "https://www.tiktok.com/electrobeat"
        },
        {
                "name": "Indie Oasis",
                "description": "Un oasis para los amantes de la música indie y alternativa.",
                "address": "Carrer de Calçat, 5, Ponent, 07011 Palma, Illes Balears",
                "phone": "5552345670",
                "profile_picture": "https://res.cloudinary.com/daxbjkj1j/image/upload/v1715625615/omwiaphmsxpmtggdcsi2.jpg",
                "banner_picture": "https://res.cloudinary.com/daxbjkj1j/image/upload/v1715625674/tci008b5y5bfhiulxgy8.png",
                "instagram": "https://www.instagram.com/indieoasis",
                "tiktok": "https://www.tiktok.com/indieoasis"
        },
        {
                "name": "Funky Groove Lounge",
                "description": "Un lugar donde la música funky y el buen ambiente se encuentran.",
                "address": "C. Marqués de Zenete, 5, Extramurs, 46007 Valencia",
                "phone": "5553456789",
                "profile_picture": "https://res.cloudinary.com/daxbjkj1j/image/upload/v1715625590/xtlyqrivagp48ijc6yma.jpg",
                "banner_picture": "https://res.cloudinary.com/daxbjkj1j/image/upload/v1715625701/cdh3owbrupqt4yyqvj79.png",
                "instagram": "https://www.instagram.com/funkygroovelounge",
                "tiktok": "https://www.tiktok.com/funkygroovelounge"
        },
        {
                "name": "Soulful",
                "description": "Una sala dedicada a la música soul y sus derivados.",
                "address": "C. de la Pl., 5, 28944 Fuenlabrada, Madrid",
                "phone": "5556789012",
                "profile_picture": "https://res.cloudinary.com/daxbjkj1j/image/upload/v1715625603/pevtqifqgshjxz9pyemd.jpg",
                "banner_picture": "https://res.cloudinary.com/daxbjkj1j/image/upload/v1715625692/gn1ruinvve1jknggiesg.png",
                "instagram": "https://www.instagram.com/soulfulmusic",
                "tiktok": "https://www.tiktok.com/soulfulmusic"
        },
        {
                "name": "Country Junction",
                "description": "Un rincón del país donde la música country es ley.",
                "address": "Calle de Covarrubias, 24, Chamberí, 28010 Madrid",
                "phone": "5559012345",
                "profile_picture": "https://res.cloudinary.com/daxbjkj1j/image/upload/v1715625585/u4b5ihymnvamusofjxyv.jpg",
                "banner_picture": "https://res.cloudinary.com/daxbjkj1j/image/upload/v1715625662/f7sfkqsdbza7a23oyovw.png",
                "instagram": "https://www.instagram.com/countryjunction",
                "tiktok": "https://www.tiktok.com/countryjunction"
        },
        {
                "name": "Alternative Underground",
                "description": "Una sala que abraza la diversidad de la música alternativa.",
                "address": "C. Patalón, 13, 10600 Plasencia, Cáceres",
                "phone": "678950334",
                "profile_picture": "https://res.cloudinary.com/daxbjkj1j/image/upload/v1715625574/bgguk8drdi6ze8hezm9z.jpg",
                "banner_picture": "https://res.cloudinary.com/daxbjkj1j/image/upload/v1715625650/xd5z463itwykqnvogf1j.png",
                "instagram": "https://www.instagram.com/alternativeunderground",
                "tiktok": "https://www.tiktok.com/alternativeunderground"
        }
]